nerm/__init__.py
nerm/crossrefs.py
nerm/gitrefs.py
nerm/nerm.py
nerm/nermfile.py
nerm/reqfile.py
nerm/satisfy.py
nerm/update.py
nerm-0.1.0.dist-info/entry_points.txt
nerm-0.1.0.dist-info/LICENSE.md
nerm-0.1.0.dist-info/WHEEL
nerm-0.1.0.dist-info/METADATA
nerm-0.1.0.dist-info/RECORD
