Metadata-Version: 2.1
Name: nerm
Version: 0.1.0
Summary: Nerm - No Effort Requirements Management
License: MIT
Author: Petteri Aimonen
Author-email: jpa@git.mail.kapsi.fi
Requires-Python: >=3.6
Classifier: License :: OSI Approved :: MIT License
Classifier: Programming Language :: Python :: 3
Classifier: Programming Language :: Python :: 3.6
Classifier: Programming Language :: Python :: 3.7
Classifier: Programming Language :: Python :: 3.8
Classifier: Programming Language :: Python :: 3.9
Requires-Dist: GitPython (>=3.1.0)
Requires-Dist: commonmark (>=0.9.0)
Requires-Dist: tomlkit (>=0.7.0)
